{"index": {"_id":"122760"}}
{"Chinese":"宏指令集", "English":"Macro instruction set"}
{"index": {"_id":"122761"}}
{"Chinese":"智能运动手环", "English":"Smart SPORTS BRACELET"}
{"index": {"_id":"122762"}}
{"Chinese":"床罩", "English":"Bedspread"}
{"index": {"_id":"122763"}}
{"Chinese":"打桩机构", "English":"Piling mechanism"}
{"index": {"_id":"122764"}}
{"Chinese":"甲基噻唑", "English":"Methyl thiazole"}
{"index": {"_id":"122765"}}
{"Chinese":"声学成像", "English":"Acoustic imaging"}
{"index": {"_id":"122766"}}
{"Chinese":"油样", "English":"Oil sample"}
{"index": {"_id":"122767"}}
{"Chinese":"相溶性", "English":"Miscibility"}
{"index": {"_id":"122768"}}
{"Chinese":"灌汤馅心", "English":"Filling heart with soup"}
{"index": {"_id":"122769"}}
{"Chinese":"地下掘进", "English":"Underground excavation"}
{"index": {"_id":"122770"}}
{"Chinese":"intel", "English":"intel"}
{"index": {"_id":"122771"}}
{"Chinese":"耳廓功能", "English":"Auricle function"}
{"index": {"_id":"122772"}}
{"Chinese":"清理水垢", "English":"Clean scale"}
{"index": {"_id":"122773"}}
{"Chinese":"特殊子帧", "English":"Special subframe"}
{"index": {"_id":"122774"}}
{"Chinese":"井下人员", "English":"Underground personnel"}
{"index": {"_id":"122775"}}
{"Chinese":"松脱机械", "English":"Loosening machine"}
{"index": {"_id":"122776"}}
{"Chinese":"谐振机器人", "English":"Resonant robot"}
{"index": {"_id":"122777"}}
{"Chinese":"兼具防淋雨", "English":"Rain proof"}
{"index": {"_id":"122778"}}
{"Chinese":"流半", "English":"Flow half"}
{"index": {"_id":"122779"}}
{"Chinese":"加香组合", "English":"Flavoring combination"}
{"index": {"_id":"122780"}}
{"Chinese":"匹配试验", "English":"Matching test"}
{"index": {"_id":"122781"}}
{"Chinese":"淡水龙虾", "English":"Freshwater lobster"}
{"index": {"_id":"122782"}}
{"Chinese":"角度显示器", "English":"Angle display"}
{"index": {"_id":"122783"}}
{"Chinese":"自然散冷式", "English":"Natural cooling type"}
{"index": {"_id":"122784"}}
{"Chinese":"鱼类烘焙", "English":"Fish baking"}
{"index": {"_id":"122785"}}
{"Chinese":"压合器", "English":"Crimper"}
{"index": {"_id":"122786"}}
{"Chinese":"小儿推拿", "English":"Pediatric massage"}
{"index": {"_id":"122787"}}
{"Chinese":"多功能管", "English":"Multifunctional tube"}
{"index": {"_id":"122788"}}
{"Chinese":"蒙乃尔", "English":"Monel "}
{"index": {"_id":"122789"}}
{"Chinese":"无光斑", "English":"No spot"}
{"index": {"_id":"122790"}}
{"Chinese":"环保油管", "English":"Environmental protection oil pipe"}
{"index": {"_id":"122791"}}
{"Chinese":"含水性", "English":"Water content"}
{"index": {"_id":"122792"}}
{"Chinese":"组织工程材料", "English":"Tissue engineering materials"}
{"index": {"_id":"122793"}}
{"Chinese":"奖品获得", "English":"Prize winning"}
{"index": {"_id":"122794"}}
{"Chinese":"盖板铆片机", "English":"Cover plate riveter"}
{"index": {"_id":"122795"}}
{"Chinese":"截面钢板弹簧", "English":"Cross section leaf spring"}
{"index": {"_id":"122796"}}
{"Chinese":"配页机构", "English":"Page mechanism"}
{"index": {"_id":"122797"}}
{"Chinese":"电荷耦合器件", "English":"Charge coupled device"}
{"index": {"_id":"122798"}}
{"Chinese":"水声信道", "English":"Underwater acoustic channel"}
{"index": {"_id":"122799"}}
{"Chinese":"家用热水", "English":"Domestic hot water"}
{"index": {"_id":"122800"}}
{"Chinese":"开关操控", "English":"Switch manipulation"}
{"index": {"_id":"122801"}}
{"Chinese":"引弧板", "English":"Arc striking plate"}
{"index": {"_id":"122802"}}
{"Chinese":"快捷连接", "English":"Quick connect"}
{"index": {"_id":"122803"}}
{"Chinese":"在线行为", "English":"Online behavior"}
{"index": {"_id":"122804"}}
{"Chinese":"形貌调控", "English":"Morphology regulation"}
{"index": {"_id":"122805"}}
{"Chinese":"人眼识别", "English":"Human eye recognition"}
{"index": {"_id":"122806"}}
{"Chinese":"酶法结合膜", "English":"Enzyme binding membrane"}
{"index": {"_id":"122807"}}
{"Chinese":"整精米", "English":"Whole milled rice"}
{"index": {"_id":"122808"}}
{"Chinese":"皮肤性病", "English":"Dermatovenereal diseases"}
{"index": {"_id":"122809"}}
{"Chinese":"空间电源", "English":"Space power supply"}
{"index": {"_id":"122810"}}
{"Chinese":"ARAIM", "English":"ARAIM"}
{"index": {"_id":"122811"}}
{"Chinese":"药品瓶", "English":"Medicine bottle"}
{"index": {"_id":"122812"}}
{"Chinese":"内容安全管理", "English":"Content security management"}
{"index": {"_id":"122813"}}
{"Chinese":"催产素", "English":"Oxytocin"}
{"index": {"_id":"122814"}}
{"Chinese":"起吊设备", "English":"Lifting equipment"}
{"index": {"_id":"122815"}}
{"Chinese":"佐餐", "English":"Eat with"}
{"index": {"_id":"122816"}}
{"Chinese":"页面调用", "English":"Page call"}
{"index": {"_id":"122817"}}
{"Chinese":"降温帽", "English":"Cooling cap"}
{"index": {"_id":"122818"}}
{"Chinese":"柱状件", "English":"Columnar piece"}
{"index": {"_id":"122819"}}
{"Chinese":"卸料设备", "English":"Unloading equipment"}
{"index": {"_id":"122820"}}
{"Chinese":"消纳能力", "English":"Absorptive capacity"}
{"index": {"_id":"122821"}}
{"Chinese":"单肩", "English":"Single shoulder"}
{"index": {"_id":"122822"}}
{"Chinese":"室内通信", "English":"Indoor communication"}
{"index": {"_id":"122823"}}
{"Chinese":"圆弧弯制", "English":"Arc bending"}
{"index": {"_id":"122824"}}
{"Chinese":"协议一致性", "English":"Agreement consistency"}
{"index": {"_id":"122825"}}
{"Chinese":"链轮传动机构", "English":"Sprocket drive mechanism"}
{"index": {"_id":"122826"}}
{"Chinese":"粮食样品", "English":"Grain sample"}
{"index": {"_id":"122827"}}
{"Chinese":"环保灭蚊", "English":"Environmental protection and mosquito control"}
{"index": {"_id":"122828"}}
{"Chinese":"组合物", "English":"Composition"}
{"index": {"_id":"122829"}}
{"Chinese":"图像浏览", "English":"Image browsing"}
{"index": {"_id":"122830"}}
{"Chinese":"医学状况", "English":"Medical condition"}
{"index": {"_id":"122831"}}
{"Chinese":"甘蔗糖蜜", "English":"Cane Molasses "}
{"index": {"_id":"122832"}}
{"Chinese":"基因转录", "English":"Gene transcription"}
{"index": {"_id":"122833"}}
{"Chinese":"钛含量", "English":"Titanium content"}
{"index": {"_id":"122834"}}
{"Chinese":"叶色", "English":"Leaf color"}
{"index": {"_id":"122835"}}
{"Chinese":"增强连接", "English":"Enhanced connection"}
{"index": {"_id":"122836"}}
{"Chinese":"治痔疮", "English":"Treatment of hemorrhoids"}
{"index": {"_id":"122837"}}
{"Chinese":"线损补偿", "English":"Line loss compensation"}
{"index": {"_id":"122838"}}
{"Chinese":"农田滴灌", "English":"Farmland drip irrigation"}
{"index": {"_id":"122839"}}
{"Chinese":"凉皮机", "English":"Cold noodle machine"}
{"index": {"_id":"122840"}}
{"Chinese":"动态锁存比较器", "English":"Dynamic latch comparator"}
{"index": {"_id":"122841"}}
{"Chinese":"续航充电", "English":"Endurance charging"}
{"index": {"_id":"122842"}}
{"Chinese":"层数可控", "English":"Controllable number of layers"}
{"index": {"_id":"122843"}}
{"Chinese":"防沙固沙", "English":"desertification control "}
{"index": {"_id":"122844"}}
{"Chinese":"全生态降解", "English":"Ecological degradation"}
{"index": {"_id":"122845"}}
{"Chinese":"生成单元", "English":"Generating unit"}
{"index": {"_id":"122846"}}
{"Chinese":"样式表", "English":"style sheet"}
{"index": {"_id":"122847"}}
{"Chinese":"克罗恩", "English":"Crohn"}
{"index": {"_id":"122848"}}
{"Chinese":"高玻璃化", "English":"High vitrification"}
{"index": {"_id":"122849"}}
{"Chinese":"水工混凝土", "English":"Hydraulic concrete"}
{"index": {"_id":"122850"}}
{"Chinese":"脱轨器", "English":"Derailer"}
{"index": {"_id":"122851"}}
{"Chinese":"默氏菌", "English":"Merella"}
{"index": {"_id":"122852"}}
{"Chinese":"双吸离心", "English":"Double suction centrifugation"}
{"index": {"_id":"122853"}}
{"Chinese":"空隙结构", "English":"Void structure"}
{"index": {"_id":"122854"}}
{"Chinese":"电商自动拣货", "English":"E-commerce automatic picking"}
{"index": {"_id":"122855"}}
{"Chinese":"触屏笔", "English":"Touch screen pen"}
{"index": {"_id":"122856"}}
{"Chinese":"视觉校正", "English":"Visual correction"}
{"index": {"_id":"122857"}}
{"Chinese":"制热运行", "English":"Heating operation"}
{"index": {"_id":"122858"}}
{"Chinese":"驱动外骨骼", "English":"Drive exoskeleton"}
{"index": {"_id":"122859"}}
{"Chinese":"电源系统", "English":"Power system"}
