{"index": {"_id":"171032"}}
{"Chinese":"插板式电源电涌", "English":"Plug in power surge"}
{"index": {"_id":"171033"}}
{"Chinese":"蒸发型空调", "English":"Steam type air conditioner"}
{"index": {"_id":"171034"}}
{"Chinese":"边缘几何特征", "English":"Edge geometry"}
{"index": {"_id":"171035"}}
{"Chinese":"统计查询", "English":"Statistical query"}
{"index": {"_id":"171036"}}
{"Chinese":"演示文档", "English":"Presentation document"}
{"index": {"_id":"171037"}}
{"Chinese":"注射鞋", "English":"Injection shoes"}
{"index": {"_id":"171038"}}
{"Chinese":"媒体同步", "English":"Media synchronization"}
{"index": {"_id":"171039"}}
{"Chinese":"微马达", "English":"Micromotor"}
{"index": {"_id":"171040"}}
{"Chinese":"贴敷膏", "English":"Paste"}
{"index": {"_id":"171041"}}
{"Chinese":"攀登器", "English":"Climber"}
{"index": {"_id":"171042"}}
{"Chinese":"张拉加强铰缝", "English":"Tensioning reinforced hinge joint"}
{"index": {"_id":"171043"}}
{"Chinese":"输送带传送", "English":"Belt conveyor"}
{"index": {"_id":"171044"}}
{"Chinese":"片自组", "English":"Slice self-assembly"}
{"index": {"_id":"171045"}}
{"Chinese":"模拟神经", "English":"Simulated nerve"}
{"index": {"_id":"171046"}}
{"Chinese":"双闸刀", "English":"Double knife switch"}
{"index": {"_id":"171047"}}
{"Chinese":"辨音成分", "English":"distinctive features "}
{"index": {"_id":"171048"}}
{"Chinese":"拨叉热校正", "English":"Fork thermal correction"}
{"index": {"_id":"171049"}}
{"Chinese":"固体加料器", "English":"Solid feeder"}
{"index": {"_id":"171050"}}
{"Chinese":"磁铁组立机构", "English":"Magnet assembly mechanism"}
{"index": {"_id":"171051"}}
{"Chinese":"倒轴", "English":"Inverted shaft"}
{"index": {"_id":"171052"}}
{"Chinese":"油田环保", "English":"Oilfield environmental protection"}
{"index": {"_id":"171053"}}
{"Chinese":"水下加工具备", "English":"Underwater processing"}
{"index": {"_id":"171054"}}
{"Chinese":"防区", "English":"a sector"}
{"index": {"_id":"171055"}}
{"Chinese":"速溶洗衣粉", "English":"Instant washing powder"}
{"index": {"_id":"171056"}}
{"Chinese":"地层坍塌压力", "English":"caving pressure "}
{"index": {"_id":"171057"}}
{"Chinese":"单据模板", "English":"Document template"}
{"index": {"_id":"171058"}}
{"Chinese":"径向旋转", "English":"Radial rotation"}
{"index": {"_id":"171059"}}
{"Chinese":"连续抛光", "English":"Continuous polishing"}
{"index": {"_id":"171060"}}
{"Chinese":"Moore-Penrose", "English":"Moore-Penrose"}
{"index": {"_id":"171061"}}
{"Chinese":"三角环", "English":"Triangular ring"}
{"index": {"_id":"171062"}}
{"Chinese":"矩形阵列", "English":"Rectangular array"}
{"index": {"_id":"171063"}}
{"Chinese":"角速度信号", "English":"Angular velocity signal"}
{"index": {"_id":"171064"}}
{"Chinese":"珐琅器", "English":"Enamel ware"}
{"index": {"_id":"171065"}}
{"Chinese":"奶瓶座", "English":"Bottle seat"}
{"index": {"_id":"171066"}}
{"Chinese":"结晶干扰", "English":"Crystal interference"}
{"index": {"_id":"171067"}}
{"Chinese":"转向检测", "English":"Steering detection"}
{"index": {"_id":"171068"}}
{"Chinese":"全天星图", "English":"All sky map"}
{"index": {"_id":"171069"}}
{"Chinese":"需辐射", "English":"Radiation required"}
{"index": {"_id":"171070"}}
{"Chinese":"统计调试", "English":"Statistical debugging"}
{"index": {"_id":"171071"}}
{"Chinese":"差压蒸馏", "English":"Differential pressure distillation"}
{"index": {"_id":"171072"}}
{"Chinese":"组合风", "English":"Combined wind"}
{"index": {"_id":"171073"}}
{"Chinese":"螺栓拉伸器", "English":"Bolt tensioner"}
{"index": {"_id":"171074"}}
{"Chinese":"制坯", "English":"Blank making"}
{"index": {"_id":"171075"}}
{"Chinese":"柱材", "English":"Column material"}
{"index": {"_id":"171076"}}
{"Chinese":"联邦滤波", "English":"Federated filtering"}
{"index": {"_id":"171077"}}
{"Chinese":"电镀机", "English":"Electroplating machine"}
{"index": {"_id":"171078"}}
{"Chinese":"薄壁螺纹管桩", "English":"Thin wall threaded pipe pile"}
{"index": {"_id":"171079"}}
{"Chinese":"六步", "English":"Six steps"}
{"index": {"_id":"171080"}}
{"Chinese":"三轴机械手", "English":"Three axis manipulator"}
{"index": {"_id":"171081"}}
{"Chinese":"中心盖", "English":"Center cover"}
{"index": {"_id":"171082"}}
{"Chinese":"乳酸甲酯", "English":"Methyl lactate"}
{"index": {"_id":"171083"}}
{"Chinese":"智能玩偶", "English":"Smart doll"}
{"index": {"_id":"171084"}}
{"Chinese":"喷射加热", "English":"Jet heating"}
{"index": {"_id":"171085"}}
{"Chinese":"暂时硬度", "English":"Temporary hardness"}
{"index": {"_id":"171086"}}
{"Chinese":"网页加载性能", "English":"Web page loading performance"}
{"index": {"_id":"171087"}}
{"Chinese":"野外供电", "English":"Field power supply"}
{"index": {"_id":"171088"}}
{"Chinese":"细胞打印", "English":"Cell printing"}
{"index": {"_id":"171089"}}
{"Chinese":"安全电线", "English":"Safety wire"}
{"index": {"_id":"171090"}}
{"Chinese":"信号转导通路", "English":"signal transduction pathway "}
{"index": {"_id":"171091"}}
{"Chinese":"输电电压补偿", "English":"Transmission voltage compensation"}
{"index": {"_id":"171092"}}
{"Chinese":"插板式谷坊", "English":"Insert plate type barn"}
{"index": {"_id":"171093"}}
{"Chinese":"绿化苗木", "English":"green seedlings "}
{"index": {"_id":"171094"}}
{"Chinese":"垄起膜", "English":"Ridging film"}
{"index": {"_id":"171095"}}
{"Chinese":"铜改性纤维", "English":"Copper modified fiber"}
{"index": {"_id":"171096"}}
{"Chinese":"肝肾不足", "English":"Deficiency of liver and kidney"}
{"index": {"_id":"171097"}}
{"Chinese":"6-通路", "English":"6-channel"}
{"index": {"_id":"171098"}}
{"Chinese":"电子标签信息", "English":"Electronic label information"}
{"index": {"_id":"171099"}}
{"Chinese":"回油机构", "English":"Oil return mechanism"}
{"index": {"_id":"171100"}}
{"Chinese":"弹性爪", "English":"Elastic claw"}
{"index": {"_id":"171101"}}
{"Chinese":"杂质或", "English":"Impurity or"}
{"index": {"_id":"171102"}}
{"Chinese":"机械臂末端", "English":"Manipulator end"}
{"index": {"_id":"171103"}}
{"Chinese":"排石片", "English":"Stone tablet"}
{"index": {"_id":"171104"}}
{"Chinese":"红茶品质", "English":"Black tea quality"}
{"index": {"_id":"171105"}}
{"Chinese":"冲片叠压", "English":"Stamping lamination"}
{"index": {"_id":"171106"}}
{"Chinese":"铜基记忆", "English":"Copper based memory"}
{"index": {"_id":"171107"}}
{"Chinese":"港穿刺", "English":"Port puncture"}
{"index": {"_id":"171108"}}
{"Chinese":"低驱动", "English":"Low drive"}
{"index": {"_id":"171109"}}
{"Chinese":"成孔机", "English":"Hole forming machine"}
{"index": {"_id":"171110"}}
{"Chinese":"窝组件", "English":"Nest assembly"}
{"index": {"_id":"171111"}}
{"Chinese":"调整焊料", "English":"Adjust solder"}
{"index": {"_id":"171112"}}
{"Chinese":"车用广告", "English":"Vehicle advertising"}
{"index": {"_id":"171113"}}
{"Chinese":"柔性电火花", "English":"Flexible spark"}
{"index": {"_id":"171114"}}
{"Chinese":"La0.8", "English":"La0.8"}
{"index": {"_id":"171115"}}
{"Chinese":"配电变压器绕组", "English":"Distribution transformer winding"}
{"index": {"_id":"171116"}}
{"Chinese":"封装量子", "English":"Encapsulated quantum"}
{"index": {"_id":"171117"}}
{"Chinese":"色素炭黑", "English":"Pigment carbon black"}
{"index": {"_id":"171118"}}
{"Chinese":"NiW", "English":"NiW"}
{"index": {"_id":"171119"}}
{"Chinese":"β-激动剂", "English":"β- Agonist"}
{"index": {"_id":"171120"}}
{"Chinese":"车门", "English":"car door"}
{"index": {"_id":"171121"}}
{"Chinese":"半自动封口", "English":"Semi automatic sealing"}
{"index": {"_id":"171122"}}
{"Chinese":"草木", "English":"Vegetation"}
{"index": {"_id":"171123"}}
{"Chinese":"燃气居民", "English":"Gas resident"}
{"index": {"_id":"171124"}}
{"Chinese":"卡槽式环刀", "English":"Grooved ring cutter"}
{"index": {"_id":"171125"}}
{"Chinese":"影像化", "English":"Imaging"}
{"index": {"_id":"171126"}}
{"Chinese":"硅酚防火", "English":"Silicophenol fire protection"}
{"index": {"_id":"171127"}}
{"Chinese":"弯折管", "English":"Bent tube"}
{"index": {"_id":"171128"}}
{"Chinese":"油漆凝聚剂", "English":"Paint coagulant"}
{"index": {"_id":"171129"}}
{"Chinese":"箱涵模心", "English":"Box culvert core"}
{"index": {"_id":"171130"}}
{"Chinese":"转化工艺", "English":"Conversion process"}
{"index": {"_id":"171131"}}
{"Chinese":"光接收表面", "English":"Light receiving surface"}
