{"index": {"_id":"577356"}}
{"Chinese":"包囊菌", "English":"Capsular bacteria"}
{"index": {"_id":"577357"}}
{"Chinese":"溶剂存储", "English":"Solvent storage"}
{"index": {"_id":"577358"}}
{"Chinese":"随汽车吊", "English":"Truck mounted crane"}
{"index": {"_id":"577359"}}
{"Chinese":"Thymalag", "English":"Thymalag"}
{"index": {"_id":"577360"}}
{"Chinese":"Fe生物", "English":"Fe biology"}
{"index": {"_id":"577361"}}
{"Chinese":"五加参火", "English":"Acanthopanax senticosus fire"}
{"index": {"_id":"577362"}}
{"Chinese":"熔边机", "English":"Edging machine"}
{"index": {"_id":"577363"}}
{"Chinese":"冷冻糕点", "English":"Frozen pastry"}
{"index": {"_id":"577364"}}
{"Chinese":"无损伤式", "English":"Non destructive"}
{"index": {"_id":"577365"}}
{"Chinese":"预防醉酒", "English":"Prevention of drunkenness"}
{"index": {"_id":"577366"}}
{"Chinese":"臀部坐垫", "English":"Hip cushion"}
{"index": {"_id":"577367"}}
{"Chinese":"船用楼梯", "English":"Marine stairs"}
{"index": {"_id":"577368"}}
{"Chinese":"保湿气膜", "English":"Moisturizing air film"}
{"index": {"_id":"577369"}}
{"Chinese":"冲洗厕所", "English":"Flush toilet"}
{"index": {"_id":"577370"}}
{"Chinese":"冷藏茶盘", "English":"Refrigerated tea tray"}
{"index": {"_id":"577371"}}
{"Chinese":"茶叶净油", "English":"Tea oil purification"}
{"index": {"_id":"577372"}}
{"Chinese":"直交轴", "English":"Orthogonal axis"}
{"index": {"_id":"577373"}}
{"Chinese":"C3435T", "English":"C3435T"}
{"index": {"_id":"577374"}}
{"Chinese":"磁性滞留", "English":"Magnetic retention"}
{"index": {"_id":"577375"}}
{"Chinese":"生产电解铜箔", "English":"Production of electrolytic copper foil"}
{"index": {"_id":"577376"}}
{"Chinese":"妇炎", "English":"Gynecological inflammation"}
{"index": {"_id":"577377"}}
{"Chinese":"隐蔽物", "English":"Concealment"}
{"index": {"_id":"577378"}}
{"Chinese":"用户数受限", "English":"Limited number of users"}
{"index": {"_id":"577379"}}
{"Chinese":"落下冲击", "English":"Falling impact"}
{"index": {"_id":"577380"}}
{"Chinese":"混料挤出", "English":"Mixed extrusion"}
{"index": {"_id":"577381"}}
{"Chinese":"照明结构", "English":"Lighting structure"}
{"index": {"_id":"577382"}}
{"Chinese":"胎儿监护仪", "English":"Fetal monitor"}
{"index": {"_id":"577383"}}
{"Chinese":"推器机构", "English":"Pusher mechanism"}
{"index": {"_id":"577384"}}
{"Chinese":"多级变速", "English":"Multistage variable speed"}
{"index": {"_id":"577385"}}
{"Chinese":"垂直管低", "English":"Vertical tube low"}
{"index": {"_id":"577386"}}
{"Chinese":"棱镜耦合测量", "English":"Prism coupling measurement"}
{"index": {"_id":"577387"}}
{"Chinese":"联盟合作", "English":"Alliance cooperation"}
{"index": {"_id":"577388"}}
{"Chinese":"兔成活率", "English":"Rabbit survival rate"}
{"index": {"_id":"577389"}}
{"Chinese":"万能卡盘", "English":"Universal chuck"}
{"index": {"_id":"577390"}}
{"Chinese":"肩锁韧带", "English":"Acromioclavicular ligament"}
{"index": {"_id":"577391"}}
{"Chinese":"阻尼杆式", "English":"Damping rod type"}
{"index": {"_id":"577392"}}
{"Chinese":"水下电焊机", "English":"Underwater welding machine"}
{"index": {"_id":"577393"}}
{"Chinese":"羰基化合成", "English":"Carbonylation synthesis"}
{"index": {"_id":"577394"}}
{"Chinese":"燃气控", "English":"Gas control"}
{"index": {"_id":"577395"}}
{"Chinese":"限制管理", "English":"Restriction management"}
{"index": {"_id":"577396"}}
{"Chinese":"枪弹分舱", "English":"Bullet compartment"}
{"index": {"_id":"577397"}}
{"Chinese":"双存储芯片", "English":"Dual memory chip"}
{"index": {"_id":"577398"}}
{"Chinese":"制动片成型", "English":"Brake pad forming"}
{"index": {"_id":"577399"}}
{"Chinese":"锥形摩擦环传动", "English":"Conical friction ring drive"}
{"index": {"_id":"577400"}}
{"Chinese":"对切电缆", "English":"Split cable"}
{"index": {"_id":"577401"}}
{"Chinese":"微米石磨", "English":"Micron stone mill"}
{"index": {"_id":"577402"}}
{"Chinese":"洗式抛丸器", "English":"Washing shot blasting device"}
{"index": {"_id":"577403"}}
{"Chinese":"延缓癌症病情", "English":"Delaying cancer"}
{"index": {"_id":"577404"}}
{"Chinese":"UE引擎", "English":"UE engine"}
{"index": {"_id":"577405"}}
{"Chinese":"运输原电池", "English":"Transport primary battery"}
{"index": {"_id":"577406"}}
{"Chinese":"指令链接能力", "English":"Instruction link capability"}
{"index": {"_id":"577407"}}
{"Chinese":"组合面板", "English":"Composite panel"}
{"index": {"_id":"577408"}}
{"Chinese":"穿索施工", "English":"Cable threading construction"}
{"index": {"_id":"577409"}}
{"Chinese":"重症病房", "English":"Intensive care unit"}
{"index": {"_id":"577410"}}
{"Chinese":"冲水电子", "English":"Flushing electron"}
{"index": {"_id":"577411"}}
{"Chinese":"灵活栅格", "English":"Flexible grid"}
{"index": {"_id":"577412"}}
{"Chinese":"冰箱消毒", "English":"Refrigerator disinfection"}
{"index": {"_id":"577413"}}
{"Chinese":"非线性电阻", "English":"Nonlinear resistance"}
{"index": {"_id":"577414"}}
{"Chinese":"单目液", "English":"Monocular solution"}
{"index": {"_id":"577415"}}
{"Chinese":"虎杖泡菜", "English":"Polygonum cuspidatum kimchi"}
{"index": {"_id":"577416"}}
{"Chinese":"倍他洛尔", "English":"Betalore"}
{"index": {"_id":"577417"}}
{"Chinese":"绵羊毛发", "English":"Sheep hair"}
{"index": {"_id":"577418"}}
{"Chinese":"分离存储", "English":"Separate storage"}
{"index": {"_id":"577419"}}
{"Chinese":"大型轮胎拆卸", "English":"Large tire disassembly"}
{"index": {"_id":"577420"}}
{"Chinese":"奶样信息", "English":"Milk sample information"}
{"index": {"_id":"577421"}}
{"Chinese":"施工用内置塔架", "English":"Built in tower for construction"}
{"index": {"_id":"577422"}}
{"Chinese":"估计电机", "English":"Estimation motor"}
{"index": {"_id":"577423"}}
{"Chinese":"三面打孔", "English":"Three side punching"}
{"index": {"_id":"577424"}}
{"Chinese":"万能夹治具", "English":"Universal clamp fixture"}
{"index": {"_id":"577425"}}
{"Chinese":"抖修正", "English":"Buffeting correction"}
{"index": {"_id":"577426"}}
{"Chinese":"戊糖乳杆菌", "English":"Lactobacillus pentosus"}
{"index": {"_id":"577427"}}
{"Chinese":"密闭式料斗", "English":"Closed hopper"}
{"index": {"_id":"577428"}}
{"Chinese":"支承压型", "English":"Supporting profiler"}
{"index": {"_id":"577429"}}
{"Chinese":"管道表面耦合", "English":"Pipe surface coupling"}
{"index": {"_id":"577430"}}
{"Chinese":"中药内裤", "English":"Traditional Chinese medicine underwear"}
{"index": {"_id":"577431"}}
{"Chinese":"垃圾分类箱", "English":"Garbage sorting bin"}
{"index": {"_id":"577432"}}
{"Chinese":"仙掌子", "English":"Fairy palm"}
{"index": {"_id":"577433"}}
{"Chinese":"伴随成分", "English":"Concomitant component"}
{"index": {"_id":"577434"}}
{"Chinese":"优质油菜", "English":"High quality rape"}
{"index": {"_id":"577435"}}
{"Chinese":"无线信号检测", "English":"Wireless signal detection"}
{"index": {"_id":"577436"}}
{"Chinese":"移动式皮带振打", "English":"Mobile belt rapping"}
{"index": {"_id":"577437"}}
{"Chinese":"同时粘贴", "English":"Paste at the same time"}
{"index": {"_id":"577438"}}
{"Chinese":"载车板", "English":"Carrier plate"}
{"index": {"_id":"577439"}}
{"Chinese":"变压器油作为", "English":"Transformer oil as"}
{"index": {"_id":"577440"}}
{"Chinese":"用角码连接", "English":"Connect with corner code"}
{"index": {"_id":"577441"}}
{"Chinese":"冷却塔水回收", "English":"Cooling tower water recovery"}
{"index": {"_id":"577442"}}
{"Chinese":"浓香白酒", "English":"Luzhou flavor Baijiu"}
{"index": {"_id":"577443"}}
{"Chinese":"任意墙面互动", "English":"Any wall interaction"}
{"index": {"_id":"577444"}}
{"Chinese":"接碳板", "English":"Carbon plate"}
{"index": {"_id":"577445"}}
{"Chinese":"边界识别", "English":"Boundary identification"}
{"index": {"_id":"577446"}}
{"Chinese":"创意酒瓶", "English":"Creative wine bottle"}
{"index": {"_id":"577447"}}
{"Chinese":"同一容器", "English":"Same container"}
{"index": {"_id":"577448"}}
{"Chinese":"多认证", "English":"Multi authentication"}
{"index": {"_id":"577449"}}
{"Chinese":"压棉杆", "English":"Cotton pressing rod"}
{"index": {"_id":"577450"}}
{"Chinese":"寻找交通", "English":"Looking for traffic"}
{"index": {"_id":"577451"}}
{"Chinese":"放水结构改进", "English":"Improvement of drainage structure"}
{"index": {"_id":"577452"}}
{"Chinese":"TCD", "English":"TCD"}
{"index": {"_id":"577453"}}
{"Chinese":"清污喷头", "English":"Cleaning nozzle"}
{"index": {"_id":"577454"}}
{"Chinese":"卡接式电连接器", "English":"Clip on electrical connector"}
