{"index": {"_id":"654853"}}
{"Chinese":"保温管穿管机", "English":"Insulation pipe threading machine"}
{"index": {"_id":"654854"}}
{"Chinese":"暖胃背心", "English":"Warm stomach vest"}
{"index": {"_id":"654855"}}
{"Chinese":"层次路由", "English":"Hierarchical routing"}
{"index": {"_id":"654856"}}
{"Chinese":"条板生产", "English":"Strip production"}
{"index": {"_id":"654857"}}
{"Chinese":"墙面交接处", "English":"Wall junction"}
{"index": {"_id":"654858"}}
{"Chinese":"夹紧力测试", "English":"Clamping force test"}
{"index": {"_id":"654859"}}
{"Chinese":"安全固态硬盘", "English":"Secure solid state drive"}
{"index": {"_id":"654860"}}
{"Chinese":"运行视野", "English":"Operational vision"}
{"index": {"_id":"654861"}}
{"Chinese":"即时消息交换", "English":"Instant message exchange"}
{"index": {"_id":"654862"}}
{"Chinese":"芒果奶膏", "English":"Mango Cream"}
{"index": {"_id":"654863"}}
{"Chinese":"磺化", "English":"sulfonation"}
{"index": {"_id":"654864"}}
{"Chinese":"弱磁探测", "English":"Weak magnetic detection"}
{"index": {"_id":"654865"}}
{"Chinese":"可行工艺", "English":"Feasible process"}
{"index": {"_id":"654866"}}
{"Chinese":"附接骨板", "English":"Attached bone plate"}
{"index": {"_id":"654867"}}
{"Chinese":"热解吸室", "English":"Thermal desorption chamber"}
{"index": {"_id":"654868"}}
{"Chinese":"复合牵伸", "English":"Compound drafting"}
{"index": {"_id":"654869"}}
{"Chinese":"硫氰", "English":"ScN "}
{"index": {"_id":"654870"}}
{"Chinese":"策略选择", "English":"Strategy selection"}
{"index": {"_id":"654871"}}
{"Chinese":"支架托架", "English":"Bracket bracket"}
{"index": {"_id":"654872"}}
{"Chinese":"荧光显示层", "English":"Fluorescent display layer"}
{"index": {"_id":"654873"}}
{"Chinese":"电压软启动电路", "English":"Voltage soft start circuit"}
{"index": {"_id":"654874"}}
{"Chinese":"水文孔", "English":"Hydrological hole"}
{"index": {"_id":"654875"}}
{"Chinese":"围条橡胶", "English":"Shroud rubber"}
{"index": {"_id":"654876"}}
{"Chinese":"盘管加热", "English":"Coil heating"}
{"index": {"_id":"654877"}}
{"Chinese":"倾角读取", "English":"Inclination reading"}
{"index": {"_id":"654878"}}
{"Chinese":"蓝莓壮阳", "English":"Blueberry aphrodisiac"}
{"index": {"_id":"654879"}}
{"Chinese":"滇重楼筛选", "English":"Screening of Paris polyphylla"}
{"index": {"_id":"654880"}}
{"Chinese":"磁环形矩近磁场", "English":"Magnetic ring moment near magnetic field"}
{"index": {"_id":"654881"}}
{"Chinese":"导波特征", "English":"Guided wave characteristics"}
{"index": {"_id":"654882"}}
{"Chinese":"催眠器中", "English":"In the hypnotic apparatus"}
{"index": {"_id":"654883"}}
{"Chinese":"三状态", "English":"Three states"}
{"index": {"_id":"654884"}}
{"Chinese":"花岗岩颗粒", "English":"Granite grain"}
{"index": {"_id":"654885"}}
{"Chinese":"单元线圈", "English":"Unit coil"}
{"index": {"_id":"654886"}}
{"Chinese":"变频", "English":"frequency conversion"}
{"index": {"_id":"654887"}}
{"Chinese":"去皮剂", "English":"Peeling agent"}
{"index": {"_id":"654888"}}
{"Chinese":"圆领包臀女衫", "English":"Round neck hip wrap blouse"}
{"index": {"_id":"654889"}}
{"Chinese":"花药采集器", "English":"Anther collector"}
{"index": {"_id":"654890"}}
{"Chinese":"制动副缸机构", "English":"Brake auxiliary cylinder mechanism"}
{"index": {"_id":"654891"}}
{"Chinese":"防摔防滑", "English":"Anti falling and anti-skid"}
{"index": {"_id":"654892"}}
{"Chinese":"安全鉴别", "English":"Security identification"}
{"index": {"_id":"654893"}}
{"Chinese":"单向频率", "English":"Unidirectional frequency"}
{"index": {"_id":"654894"}}
{"Chinese":"精密封装", "English":"Precision packaging"}
{"index": {"_id":"654895"}}
{"Chinese":"立式机舱", "English":"Vertical engine room"}
{"index": {"_id":"654896"}}
{"Chinese":"元片", "English":"Yuan Pian"}
{"index": {"_id":"654897"}}
{"Chinese":"车载路障识别", "English":"Vehicle roadblock identification"}
{"index": {"_id":"654898"}}
{"Chinese":"假体脱位", "English":"Prosthesis dislocation"}
{"index": {"_id":"654899"}}
{"Chinese":"树脂酯化", "English":"Resin esterification"}
{"index": {"_id":"654900"}}
{"Chinese":"极片切条", "English":"Pole slice slitting"}
{"index": {"_id":"654901"}}
{"Chinese":"篮球场层", "English":"Basketball court floor"}
{"index": {"_id":"654902"}}
{"Chinese":"组合脱酸除尘", "English":"Combined deacidification and dust removal"}
{"index": {"_id":"654903"}}
{"Chinese":"微功率损耗", "English":"Micro power loss"}
{"index": {"_id":"654904"}}
{"Chinese":"主机出入度", "English":"Host access"}
{"index": {"_id":"654905"}}
{"Chinese":"弧形光源", "English":"Arc light source"}
{"index": {"_id":"654906"}}
{"Chinese":"日灼", "English":"Sunburn"}
{"index": {"_id":"654907"}}
{"Chinese":"草编", "English":"Straw weaving"}
{"index": {"_id":"654908"}}
{"Chinese":"所述遮挡组件", "English":"The shielding component"}
{"index": {"_id":"654909"}}
{"Chinese":"光缆自动排线", "English":"Automatic cable arrangement"}
{"index": {"_id":"654910"}}
{"Chinese":"移动式谷物", "English":"Mobile grain"}
{"index": {"_id":"654911"}}
{"Chinese":"最小路径", "English":"Minimum path"}
{"index": {"_id":"654912"}}
{"Chinese":"传动", "English":"transmission"}
{"index": {"_id":"654913"}}
{"Chinese":"轴封供汽加", "English":"Shaft seal steam supply heater"}
{"index": {"_id":"654914"}}
{"Chinese":"启闭特性", "English":"Opening and closing characteristics"}
{"index": {"_id":"654915"}}
{"Chinese":"三钴碳", "English":"Tri cobalt carbon"}
{"index": {"_id":"654916"}}
{"Chinese":"外阴湿疹", "English":"Vulvar eczema"}
{"index": {"_id":"654917"}}
{"Chinese":"行驶断电", "English":"Driving power failure"}
{"index": {"_id":"654918"}}
{"Chinese":"传感测量光路", "English":"Sensing measurement optical path"}
{"index": {"_id":"654919"}}
{"Chinese":"防水封盖", "English":"Waterproof cover"}
{"index": {"_id":"654920"}}
{"Chinese":"堵塞筛分仓", "English":"Blocking screening bin"}
{"index": {"_id":"654921"}}
{"Chinese":"顶层填缝剂", "English":"Top layer joint sealant"}
{"index": {"_id":"654922"}}
{"Chinese":"被吸附", "English":"Adsorbed"}
{"index": {"_id":"654923"}}
{"Chinese":"生产防止", "English":"Production prevention"}
{"index": {"_id":"654924"}}
{"Chinese":"筒式烘干箱", "English":"Drum drying oven"}
{"index": {"_id":"654925"}}
{"Chinese":"双臂打磨机", "English":"Double arm grinder"}
{"index": {"_id":"654926"}}
{"Chinese":"积水防爆", "English":"Ponding explosion proof"}
{"index": {"_id":"654927"}}
{"Chinese":"滚槽模具", "English":"Grooving die"}
{"index": {"_id":"654928"}}
{"Chinese":"斯码功能", "English":"Si code function"}
{"index": {"_id":"654929"}}
{"Chinese":"兼作铅笔帽", "English":"Also used as pencil cap"}
{"index": {"_id":"654930"}}
{"Chinese":"地面吸尘", "English":"Ground dust collection"}
{"index": {"_id":"654931"}}
{"Chinese":"机构", "English":"mechanism"}
{"index": {"_id":"654932"}}
{"Chinese":"阅读文本", "English":"Reading text"}
{"index": {"_id":"654933"}}
{"Chinese":"定位刷新", "English":"Location refresh"}
{"index": {"_id":"654934"}}
{"Chinese":"差分转单", "English":"Differential transfer order"}
{"index": {"_id":"654935"}}
{"Chinese":"绝缘低压电力电缆", "English":"Insulated low voltage power cable"}
{"index": {"_id":"654936"}}
{"Chinese":"风叶发电", "English":"Wind blade power generation"}
{"index": {"_id":"654937"}}
{"Chinese":"系统安全校验", "English":"System security verification"}
{"index": {"_id":"654938"}}
{"Chinese":"产品着色", "English":"Product coloring"}
{"index": {"_id":"654939"}}
{"Chinese":"合成茶", "English":"Synthetic tea"}
{"index": {"_id":"654940"}}
{"Chinese":"梨汁醋饮料", "English":"Pear juice vinegar beverage"}
{"index": {"_id":"654941"}}
{"Chinese":"外磁转子", "English":"External magnetic rotor"}
{"index": {"_id":"654942"}}
{"Chinese":"滑牙预防", "English":"Prevention of slippery teeth"}
{"index": {"_id":"654943"}}
{"Chinese":"自架式", "English":"Self supporting"}
{"index": {"_id":"654944"}}
{"Chinese":"眼科视力", "English":"Ophthalmic vision"}
{"index": {"_id":"654945"}}
{"Chinese":"贮存一体式", "English":"Storage integrated"}
{"index": {"_id":"654946"}}
{"Chinese":"芯药枕", "English":"Core medicine pillow"}
{"index": {"_id":"654947"}}
{"Chinese":"均衡扭矩", "English":"Equalizing torque"}
{"index": {"_id":"654948"}}
{"Chinese":"侧面V型槽", "English":"Side V-groove"}
{"index": {"_id":"654949"}}
{"Chinese":"唾液板", "English":"Salivary plate"}
{"index": {"_id":"654950"}}
{"Chinese":"采摘花椒", "English":"Picking pepper"}
{"index": {"_id":"654951"}}
{"Chinese":"感压式", "English":"Pressure sensing type"}
{"index": {"_id":"654952"}}
{"Chinese":"驱动工具滑台", "English":"Drive tool slide"}
